phydcm/__init__.py
phydcm/config.py
phydcm/create_datasets.py
phydcm/medvit_model.py
phydcm/predict.py
phydcm/train.py
phydcm/utils.py
phydcm/models/ct_best_model.keras
phydcm/models/ct_labels.json
phydcm/models/mri_best_model.keras
phydcm/models/mri_labels.json
phydcm/models/pet_best_model.keras
phydcm/models/pet_labels.json
phydcm-2.4.0.dist-info/licenses/LICENSE
phydcm-2.4.0.dist-info/METADATA
phydcm-2.4.0.dist-info/WHEEL
phydcm-2.4.0.dist-info/top_level.txt
phydcm-2.4.0.dist-info/RECORD
